[{"id":"ajofrin-id45001","id_provincia":"45","name":"Ajofr\u00edn"},{"id":"alameda-de-la-sagra-id45002","id_provincia":"45","name":"Alameda de la Sagra"},{"id":"albarreal-de-tajo-id45003","id_provincia":"45","name":"Albarreal de Tajo"},{"id":"alcabon-id45004","id_provincia":"45","name":"Alcab\u00f3n"},{"id":"alcanizo-id45005","id_provincia":"45","name":"Alca\u00f1izo"},{"id":"alcaudete-de-la-jara-id45006","id_provincia":"45","name":"Alcaudete de la Jara"},{"id":"alcolea-de-tajo-id45007","id_provincia":"45","name":"Alcolea de Tajo"},{"id":"aldea-en-cabo-id45008","id_provincia":"45","name":"Aldea en Cabo"},{"id":"aldeanueva-de-barbarroya-id45009","id_provincia":"45","name":"Aldeanueva de Barbarroya"},{"id":"aldeanueva-de-san-bartolome-id45010","id_provincia":"45","name":"Aldeanueva de San Bartolom\u00e9"},{"id":"almendral-de-la-canada-id45011","id_provincia":"45","name":"Almendral de la Ca\u00f1ada"},{"id":"almonacid-de-toledo-id45012","id_provincia":"45","name":"Almonacid de Toledo"},{"id":"almorox-id45013","id_provincia":"45","name":"Almorox"},{"id":"anover-de-tajo-id45014","id_provincia":"45","name":"A\u00f1over de Tajo"},{"id":"arcicollar-id45015","id_provincia":"45","name":"Arcic\u00f3llar"},{"id":"arges-id45016","id_provincia":"45","name":"Arg\u00e9s"},{"id":"azutan-id45017","id_provincia":"45","name":"Azut\u00e1n"},{"id":"barcience-id45018","id_provincia":"45","name":"Barcience"},{"id":"bargas-id45019","id_provincia":"45","name":"Bargas"},{"id":"belvis-de-la-jara-id45020","id_provincia":"45","name":"Belv\u00eds de la Jara"},{"id":"borox-id45021","id_provincia":"45","name":"Borox"},{"id":"buenaventura-id45022","id_provincia":"45","name":"Buenaventura"},{"id":"burguillos-de-toledo-id45023","id_provincia":"45","name":"Burguillos de Toledo"},{"id":"burujon-id45024","id_provincia":"45","name":"Buruj\u00f3n"},{"id":"cabanas-de-la-sagra-id45025","id_provincia":"45","name":"Caba\u00f1as de la Sagra"},{"id":"cabanas-de-yepes-id45026","id_provincia":"45","name":"Caba\u00f1as de Yepes"},{"id":"cabezamesada-id45027","id_provincia":"45","name":"Cabezamesada"},{"id":"calera-y-chozas-id45028","id_provincia":"45","name":"Calera y Chozas"},{"id":"caleruela-id45029","id_provincia":"45","name":"Caleruela"},{"id":"calzada-de-oropesa-id45030","id_provincia":"45","name":"Calzada de Oropesa"},{"id":"camarena-id45031","id_provincia":"45","name":"Camarena"},{"id":"camarenilla-id45032","id_provincia":"45","name":"Camarenilla"},{"id":"campillo-de-la-jara-el-id45033","id_provincia":"45","name":"Campillo de la Jara, El"},{"id":"camunas-id45034","id_provincia":"45","name":"Camu\u00f1as"},{"id":"cardiel-de-los-montes-id45035","id_provincia":"45","name":"Cardiel de los Montes"},{"id":"carmena-id45036","id_provincia":"45","name":"Carmena"},{"id":"carpio-de-tajo-el-id45037","id_provincia":"45","name":"Carpio de Tajo, El"},{"id":"carranque-id45038","id_provincia":"45","name":"Carranque"},{"id":"carriches-id45039","id_provincia":"45","name":"Carriches"},{"id":"casar-de-escalona-el-id45040","id_provincia":"45","name":"Casar de Escalona, El"},{"id":"casarrubios-del-monte-id45041","id_provincia":"45","name":"Casarrubios del Monte"},{"id":"casasbuenas-id45042","id_provincia":"45","name":"Casasbuenas"},{"id":"castillo-de-bayuela-id45043","id_provincia":"45","name":"Castillo de Bayuela"},{"id":"cazalegas-id45045","id_provincia":"45","name":"Cazalegas"},{"id":"cebolla-id45046","id_provincia":"45","name":"Cebolla"},{"id":"cedillo-del-condado-id45047","id_provincia":"45","name":"Cedillo del Condado"},{"id":"cerralbos-los-id45048","id_provincia":"45","name":"Cerralbos, Los"},{"id":"cervera-de-los-montes-id45049","id_provincia":"45","name":"Cervera de los Montes"},{"id":"chozas-de-canales-id45056","id_provincia":"45","name":"Chozas de Canales"},{"id":"chueca-id45057","id_provincia":"45","name":"Chueca"},{"id":"ciruelos-id45050","id_provincia":"45","name":"Ciruelos"},{"id":"cobeja-id45051","id_provincia":"45","name":"Cobeja"},{"id":"cobisa-id45052","id_provincia":"45","name":"Cobisa"},{"id":"consuegra-id45053","id_provincia":"45","name":"Consuegra"},{"id":"corral-de-almaguer-id45054","id_provincia":"45","name":"Corral de Almaguer"},{"id":"cuerva-id45055","id_provincia":"45","name":"Cuerva"},{"id":"domingo-perez-id45058","id_provincia":"45","name":"Domingo P\u00e9rez"},{"id":"dosbarrios-id45059","id_provincia":"45","name":"Dosbarrios"},{"id":"erustes-id45060","id_provincia":"45","name":"Erustes"},{"id":"escalona-id45061","id_provincia":"45","name":"Escalona"},{"id":"escalonilla-id45062","id_provincia":"45","name":"Escalonilla"},{"id":"espinoso-del-rey-id45063","id_provincia":"45","name":"Espinoso del Rey"},{"id":"esquivias-id45064","id_provincia":"45","name":"Esquivias"},{"id":"estrella-la-id45065","id_provincia":"45","name":"Estrella, La"},{"id":"fuensalida-id45066","id_provincia":"45","name":"Fuensalida"},{"id":"galvez-id45067","id_provincia":"45","name":"G\u00e1lvez"},{"id":"garciotum-id45068","id_provincia":"45","name":"Garciotum"},{"id":"gerindote-id45069","id_provincia":"45","name":"Gerindote"},{"id":"guadamur-id45070","id_provincia":"45","name":"Guadamur"},{"id":"guardia-la-id45071","id_provincia":"45","name":"Guardia, La"},{"id":"herencias-las-id45072","id_provincia":"45","name":"Herencias, Las"},{"id":"herreruela-de-oropesa-id45073","id_provincia":"45","name":"Herreruela de Oropesa"},{"id":"hinojosa-de-san-vicente-id45074","id_provincia":"45","name":"Hinojosa de San Vicente"},{"id":"hontanar-id45075","id_provincia":"45","name":"Hontanar"},{"id":"hormigos-id45076","id_provincia":"45","name":"Hormigos"},{"id":"huecas-id45077","id_provincia":"45","name":"Huecas"},{"id":"huerta-de-valdecarabanos-id45078","id_provincia":"45","name":"Huerta de Valdecar\u00e1banos"},{"id":"iglesuela-la-id45079","id_provincia":"45","name":"Iglesuela, La"},{"id":"illan-de-vacas-id45080","id_provincia":"45","name":"Ill\u00e1n de Vacas"},{"id":"illescas-id45081","id_provincia":"45","name":"Illescas"},{"id":"lagartera-id45082","id_provincia":"45","name":"Lagartera"},{"id":"layos-id45083","id_provincia":"45","name":"Layos"},{"id":"lillo-id45084","id_provincia":"45","name":"Lillo"},{"id":"lominchar-id45085","id_provincia":"45","name":"Lominchar"},{"id":"lucillos-id45086","id_provincia":"45","name":"Lucillos"},{"id":"madridejos-id45087","id_provincia":"45","name":"Madridejos"},{"id":"magan-id45088","id_provincia":"45","name":"Mag\u00e1n"},{"id":"malpica-de-tajo-id45089","id_provincia":"45","name":"Malpica de Tajo"},{"id":"manzaneque-id45090","id_provincia":"45","name":"Manzaneque"},{"id":"maqueda-id45091","id_provincia":"45","name":"Maqueda"},{"id":"marjaliza-id45092","id_provincia":"45","name":"Marjaliza"},{"id":"marrupe-id45093","id_provincia":"45","name":"Marrupe"},{"id":"mascaraque-id45094","id_provincia":"45","name":"Mascaraque"},{"id":"mata-la-id45095","id_provincia":"45","name":"Mata, La"},{"id":"mazarambroz-id45096","id_provincia":"45","name":"Mazarambroz"},{"id":"mejorada-id45097","id_provincia":"45","name":"Mejorada"},{"id":"menasalbas-id45098","id_provincia":"45","name":"Menasalbas"},{"id":"mentrida-id45099","id_provincia":"45","name":"M\u00e9ntrida"},{"id":"mesegar-de-tajo-id45100","id_provincia":"45","name":"Mesegar de Tajo"},{"id":"miguel-esteban-id45101","id_provincia":"45","name":"Miguel Esteban"},{"id":"mocejon-id45102","id_provincia":"45","name":"Mocej\u00f3n"},{"id":"mohedas-de-la-jara-id45103","id_provincia":"45","name":"Mohedas de la Jara"},{"id":"montearagon-id45104","id_provincia":"45","name":"Montearag\u00f3n"},{"id":"montesclaros-id45105","id_provincia":"45","name":"Montesclaros"},{"id":"mora-id45106","id_provincia":"45","name":"Mora"},{"id":"nambroca-id45107","id_provincia":"45","name":"Nambroca"},{"id":"nava-de-ricomalillo-la-id45108","id_provincia":"45","name":"Nava de Ricomalillo, La"},{"id":"navahermosa-id45109","id_provincia":"45","name":"Navahermosa"},{"id":"navalcan-id45110","id_provincia":"45","name":"Navalc\u00e1n"},{"id":"navalmoralejo-id45111","id_provincia":"45","name":"Navalmoralejo"},{"id":"navalmorales-los-id45112","id_provincia":"45","name":"Navalmorales, Los"},{"id":"navalucillos-los-id45113","id_provincia":"45","name":"Navalucillos, Los"},{"id":"navamorcuende-id45114","id_provincia":"45","name":"Navamorcuende"},{"id":"noblejas-id45115","id_provincia":"45","name":"Noblejas"},{"id":"noez-id45116","id_provincia":"45","name":"Noez"},{"id":"nombela-id45117","id_provincia":"45","name":"Nombela"},{"id":"noves-id45118","id_provincia":"45","name":"Nov\u00e9s"},{"id":"numancia-de-la-sagra-id45119","id_provincia":"45","name":"Numancia de la Sagra"},{"id":"nuno-gomez-id45120","id_provincia":"45","name":"Nu\u00f1o G\u00f3mez"},{"id":"ocana-id45121","id_provincia":"45","name":"Oca\u00f1a"},{"id":"olias-del-rey-id45122","id_provincia":"45","name":"Ol\u00edas del Rey"},{"id":"ontigola-id45123","id_provincia":"45","name":"Ont\u00edgola"},{"id":"orgaz-id45124","id_provincia":"45","name":"Orgaz"},{"id":"oropesa-id45125","id_provincia":"45","name":"Oropesa"},{"id":"otero-id45126","id_provincia":"45","name":"Otero"},{"id":"palomeque-id45127","id_provincia":"45","name":"Palomeque"},{"id":"pantoja-id45128","id_provincia":"45","name":"Pantoja"},{"id":"paredes-de-escalona-id45129","id_provincia":"45","name":"Paredes de Escalona"},{"id":"parrillas-id45130","id_provincia":"45","name":"Parrillas"},{"id":"pelahustan-id45131","id_provincia":"45","name":"Pelahust\u00e1n"},{"id":"pepino-id45132","id_provincia":"45","name":"Pepino"},{"id":"polan-id45133","id_provincia":"45","name":"Pol\u00e1n"},{"id":"portillo-de-toledo-id45134","id_provincia":"45","name":"Portillo de Toledo"},{"id":"puebla-de-almoradiel-la-id45135","id_provincia":"45","name":"Puebla de Almoradiel, La"},{"id":"puebla-de-montalban-la-id45136","id_provincia":"45","name":"Puebla de Montalb\u00e1n, La"},{"id":"pueblanueva-la-id45137","id_provincia":"45","name":"Pueblanueva, La"},{"id":"puente-del-arzobispo-el-id45138","id_provincia":"45","name":"Puente del Arzobispo, El"},{"id":"puerto-de-san-vicente-id45139","id_provincia":"45","name":"Puerto de San Vicente"},{"id":"pulgar-id45140","id_provincia":"45","name":"Pulgar"},{"id":"quero-id45141","id_provincia":"45","name":"Quero"},{"id":"quintanar-de-la-orden-id45142","id_provincia":"45","name":"Quintanar de la Orden"},{"id":"quismondo-id45143","id_provincia":"45","name":"Quismondo"},{"id":"real-de-san-vicente-el-id45144","id_provincia":"45","name":"Real de San Vicente, El"},{"id":"recas-id45145","id_provincia":"45","name":"Recas"},{"id":"retamoso-de-la-jara-id45146","id_provincia":"45","name":"Retamoso de la Jara"},{"id":"rielves-id45147","id_provincia":"45","name":"Rielves"},{"id":"robledo-del-mazo-id45148","id_provincia":"45","name":"Robledo del Mazo"},{"id":"romeral-el-id45149","id_provincia":"45","name":"Romeral, El"},{"id":"san-bartolome-de-las-abiertas-id45150","id_provincia":"45","name":"San Bartolom\u00e9 de las Abiertas"},{"id":"san-martin-de-montalban-id45151","id_provincia":"45","name":"San Mart\u00edn de Montalb\u00e1n"},{"id":"san-martin-de-pusa-id45152","id_provincia":"45","name":"San Mart\u00edn de Pusa"},{"id":"san-pablo-de-los-montes-id45153","id_provincia":"45","name":"San Pablo de los Montes"},{"id":"san-roman-de-los-montes-id45154","id_provincia":"45","name":"San Rom\u00e1n de los Montes"},{"id":"santa-ana-de-pusa-id45155","id_provincia":"45","name":"Santa Ana de Pusa"},{"id":"santa-cruz-de-la-zarza-id45156","id_provincia":"45","name":"Santa Cruz de la Zarza"},{"id":"santa-cruz-del-retamar-id45157","id_provincia":"45","name":"Santa Cruz del Retamar"},{"id":"santa-olalla-id45158","id_provincia":"45","name":"Santa Olalla"},{"id":"santo-domingo-caudilla-val-de-santo-domingo-id45901","id_provincia":"45","name":"Santo Domingo-Caudilla"},{"id":"sartajada-id45159","id_provincia":"45","name":"Sartajada"},{"id":"segurilla-id45160","id_provincia":"45","name":"Segurilla"},{"id":"sesena-id45161","id_provincia":"45","name":"Sese\u00f1a"},{"id":"sevilleja-de-la-jara-id45162","id_provincia":"45","name":"Sevilleja de la Jara"},{"id":"sonseca-id45163","id_provincia":"45","name":"Sonseca"},{"id":"sotillo-de-las-palomas-id45164","id_provincia":"45","name":"Sotillo de las Palomas"},{"id":"talavera-de-la-reina-id45165","id_provincia":"45","name":"Talavera de la Reina"},{"id":"tembleque-id45166","id_provincia":"45","name":"Tembleque"},{"id":"toboso-el-id45167","id_provincia":"45","name":"Toboso, El"},{"id":"toledo-id45168","id_provincia":"45","name":"Toledo"},{"id":"torralba-de-oropesa-id45169","id_provincia":"45","name":"Torralba de Oropesa"},{"id":"torrecilla-de-la-jara-id45170","id_provincia":"45","name":"Torrecilla de la Jara"},{"id":"torre-de-esteban-hambran-la-id45171","id_provincia":"45","name":"Torre de Esteban Hambr\u00e1n, La"},{"id":"torrico-id45172","id_provincia":"45","name":"Torrico"},{"id":"torrijos-id45173","id_provincia":"45","name":"Torrijos"},{"id":"totanes-id45174","id_provincia":"45","name":"Totan\u00e9s"},{"id":"turleque-id45175","id_provincia":"45","name":"Turleque"},{"id":"ugena-id45176","id_provincia":"45","name":"Ugena"},{"id":"urda-id45177","id_provincia":"45","name":"Urda"},{"id":"valdeverdeja-id45179","id_provincia":"45","name":"Valdeverdeja"},{"id":"valmojado-id45180","id_provincia":"45","name":"Valmojado"},{"id":"velada-id45181","id_provincia":"45","name":"Velada"},{"id":"ventas-con-pena-aguilera-las-id45182","id_provincia":"45","name":"Ventas con Pe\u00f1a Aguilera, Las"},{"id":"ventas-de-retamosa-las-id45183","id_provincia":"45","name":"Ventas de Retamosa, Las"},{"id":"ventas-de-san-julian-las-id45184","id_provincia":"45","name":"Ventas de San Juli\u00e1n, Las"},{"id":"villacanas-id45185","id_provincia":"45","name":"Villaca\u00f1as"},{"id":"villa-de-don-fadrique-la-id45186","id_provincia":"45","name":"Villa de Don Fadrique, La"},{"id":"villafranca-de-los-caballeros-id45187","id_provincia":"45","name":"Villafranca de los Caballeros"},{"id":"villaluenga-de-la-sagra-id45188","id_provincia":"45","name":"Villaluenga de la Sagra"},{"id":"villamiel-de-toledo-id45189","id_provincia":"45","name":"Villamiel de Toledo"},{"id":"villaminaya-id45190","id_provincia":"45","name":"Villaminaya"},{"id":"villamuelas-id45191","id_provincia":"45","name":"Villamuelas"},{"id":"villanueva-de-alcardete-id45192","id_provincia":"45","name":"Villanueva de Alcardete"},{"id":"villanueva-de-bogas-id45193","id_provincia":"45","name":"Villanueva de Bogas"},{"id":"villarejo-de-montalban-id45194","id_provincia":"45","name":"Villarejo de Montalb\u00e1n"},{"id":"villarrubia-de-santiago-id45195","id_provincia":"45","name":"Villarrubia de Santiago"},{"id":"villaseca-de-la-sagra-id45196","id_provincia":"45","name":"Villaseca de la Sagra"},{"id":"villasequilla-id45197","id_provincia":"45","name":"Villasequilla"},{"id":"villatobas-id45198","id_provincia":"45","name":"Villatobas"},{"id":"viso-de-san-juan-el-id45199","id_provincia":"45","name":"Viso de San Juan, El"},{"id":"yebenes-los-id45200","id_provincia":"45","name":"Y\u00e9benes, Los"},{"id":"yeles-id45201","id_provincia":"45","name":"Yeles"},{"id":"yepes-id45202","id_provincia":"45","name":"Yepes"},{"id":"yuncler-id45203","id_provincia":"45","name":"Yuncler"},{"id":"yunclillos-id45204","id_provincia":"45","name":"Yunclillos"},{"id":"yuncos-id45205","id_provincia":"45","name":"Yuncos"}]