[{"id":"agaete-id35001","id_provincia":"35","name":"Agaete"},{"id":"aguimes-id35002","id_provincia":"35","name":"Ag\u00fcimes"},{"id":"aldea-de-san-nicolas-la-id35020","id_provincia":"35","name":"Aldea de San Nicol\u00e1s, La"},{"id":"antigua-id35003","id_provincia":"35","name":"Antigua"},{"id":"arrecife-id35004","id_provincia":"35","name":"Arrecife"},{"id":"artenara-id35005","id_provincia":"35","name":"Artenara"},{"id":"arucas-id35006","id_provincia":"35","name":"Arucas"},{"id":"betancuria-id35007","id_provincia":"35","name":"Betancuria"},{"id":"firgas-id35008","id_provincia":"35","name":"Firgas"},{"id":"galdar-id35009","id_provincia":"35","name":"G\u00e1ldar"},{"id":"haria-id35010","id_provincia":"35","name":"Har\u00eda"},{"id":"ingenio-id35011","id_provincia":"35","name":"Ingenio"},{"id":"mogan-id35012","id_provincia":"35","name":"Mog\u00e1n"},{"id":"moya-id35013","id_provincia":"35","name":"Moya"},{"id":"oliva-la-id35014","id_provincia":"35","name":"Oliva, La"},{"id":"pajara-id35015","id_provincia":"35","name":"P\u00e1jara"},{"id":"palmas-de-gran-canaria-las-id35016","id_provincia":"35","name":"Palmas de Gran Canaria, Las"},{"id":"puerto-del-rosario-id35017","id_provincia":"35","name":"Puerto del Rosario"},{"id":"san-bartolome-id35018","id_provincia":"35","name":"San Bartolom\u00e9"},{"id":"san-bartolome-de-tirajana-id35019","id_provincia":"35","name":"San Bartolom\u00e9 de Tirajana"},{"id":"santa-brigida-id35021","id_provincia":"35","name":"Santa Br\u00edgida"},{"id":"santa-lucia-de-tirajana-id35022","id_provincia":"35","name":"Santa Luc\u00eda de Tirajana"},{"id":"santa-maria-de-guia-de-gran-canaria-id35023","id_provincia":"35","name":"Santa Mar\u00eda de Gu\u00eda de Gran Canaria"},{"id":"teguise-id35024","id_provincia":"35","name":"Teguise"},{"id":"tejeda-id35025","id_provincia":"35","name":"Tejeda"},{"id":"telde-id35026","id_provincia":"35","name":"Telde"},{"id":"teror-id35027","id_provincia":"35","name":"Teror"},{"id":"tias-id35028","id_provincia":"35","name":"T\u00edas"},{"id":"tinajo-id35029","id_provincia":"35","name":"Tinajo"},{"id":"tuineje-id35030","id_provincia":"35","name":"Tuineje"},{"id":"valleseco-id35032","id_provincia":"35","name":"Valleseco"},{"id":"valsequillo-de-gran-canaria-id35031","id_provincia":"35","name":"Valsequillo de Gran Canaria"},{"id":"vega-de-san-mateo-id35033","id_provincia":"35","name":"Vega de San Mateo"},{"id":"yaiza-id35034","id_provincia":"35","name":"Yaiza"}]